{
	"keys": [
		{	
			"key": "1234-5678-9012-3455",
			"allowed_ips": "103.80.239.85"
		},
		{
			"key": "1234-5678-9012-3456",
			"allowed_ips": "147.135.85.213"
		},
		{
			"key": "1234-5678-9012-3457",
			"allowed_ips": "103.138.40.2"
		},
		{
			"key": "key4",
			"allowed_ips": "192.168.1.110"
		},
		{
			"key": "key5",
			"allowed_ips": "192.168.1.120"
		},
		{
			"key": "key6",
			"allowed_ips": "192.168.1.125"
		},
		{
			"key": "key7",
			"allowed_ips": "192.168.1.130"
		},
		{
			"key": "key8",
			"allowed_ips": "192.168.1.135"
		}
	]
}
